crypto_explorer/__init__.py
crypto_explorer/api/__init__.py
crypto_explorer/api/account_api.py
crypto_explorer/api/blockscout_api.py
crypto_explorer/api/ccxt_api.py
crypto_explorer/api/moralis_api.py
crypto_explorer/api/quicknode_api.py
crypto_explorer/custom_exceptions/__init__.py
crypto_explorer/custom_exceptions/api_error.py
crypto_explorer/custom_exceptions/invalid_arguments.py
crypto_explorer/utils/__init__.py
crypto_explorer/utils/kline_utils.py
crypto_explorer/utils/log_handler.py
crypto_explorer/utils/time_utils.py
cryptoexplorer-1.3.dist-info/METADATA
cryptoexplorer-1.3.dist-info/WHEEL
cryptoexplorer-1.3.dist-info/top_level.txt
cryptoexplorer-1.3.dist-info/RECORD
