Metadata-Version: 2.4
Name: CryptoExplorer
Version: 1.3
Summary: Simplified cryptocurrency and blockchain data extraction
Author: Archie Marques
Classifier: Programming Language :: Python :: 3
Classifier: License :: OSI Approved :: MIT License
Classifier: Operating System :: OS Independent
Requires-Python: >=3.10
Requires-Dist: typing-extensions==4.13.2
Requires-Dist: tqdm>=4.65.0
Requires-Dist: klib>=1.1.1
Requires-Dist: ccxt>=4.0.86
Requires-Dist: pandas>=2.0.3
Requires-Dist: pyarrow>=12.0.0
Requires-Dist: numpy>=1.23.5
Requires-Dist: moralis>=0.1.49
Requires-Dist: sqlalchemy>=2.0.41
Requires-Dist: psycopg2>=2.9.10
Requires-Dist: pytest
Dynamic: author
Dynamic: classifier
Dynamic: description
Dynamic: description-content-type
Dynamic: requires-dist
Dynamic: requires-python
Dynamic: summary
